yta_core/__init__.py
yta_core/audio/__init__.py
yta_core/audio/transcription.py
yta_core/builder/__init__.py
yta_core/builder/ai_image_builder.py
yta_core/builder/ai_video_builder.py
yta_core/builder/custom_stock_builder.py
yta_core/builder/dataclasses.py
yta_core/builder/effect_builder.py
yta_core/builder/enums.py
yta_core/builder/greenscreen_builder.py
yta_core/builder/image_builder.py
yta_core/builder/meme_builder.py
yta_core/builder/music/__init__.py
yta_core/builder/music/enums.py
yta_core/builder/music/generator.py
yta_core/builder/premade_builder.py
yta_core/builder/sound_builder.py
yta_core/builder/stock/__init__.py
yta_core/builder/stock_builder.py
yta_core/builder/text_builder.py
yta_core/builder/utils.py
yta_core/builder/video_builder.py
yta_core/builder/voice_narration/__init__.py
yta_core/builder/voice_narration/enums.py
yta_core/builder/youtube/__init__.py
yta_core/builder/youtube/enums.py
yta_core/builder/youtube_video_builder.py
yta_core/classes/__init__.py
yta_core/classes/enhancement.py
yta_core/classes/enhancement_json.py
yta_core/classes/music_json.py
yta_core/classes/project.py
yta_core/classes/project_raw.py
yta_core/classes/project_validated.py
yta_core/classes/segment.py
yta_core/classes/segment_json.py
yta_core/classes/voice_narration_json.py
yta_core/configuration/__init__.py
yta_core/configuration/condition/__init__.py
yta_core/configuration/condition/mandatory.py
yta_core/configuration/condition/optional.py
yta_core/database/__init__.py
yta_core/database/dataclasses.py
yta_core/edition_manual/__init__.py
yta_core/edition_manual/enums.py
yta_core/edition_manual/term.py
yta_core/enums/__init__.py
yta_core/enums/component.py
yta_core/enums/field.py
yta_core/enums/field_v2.py
yta_core/enums/mode.py
yta_core/enums/origin.py
yta_core/enums/start.py
yta_core/enums/status.py
yta_core/enums/string_duration.py
yta_core/enums/type.py
yta_core/settings.py
yta_core/shortcodes/__init__.py
yta_core/shortcodes/parser.py
yta_core/shortcodes/tag.py
yta_core-0.0.21.dist-info/LICENSE
yta_core-0.0.21.dist-info/METADATA
yta_core-0.0.21.dist-info/WHEEL
yta_core-0.0.21.dist-info/RECORD
