Metadata-Version: 2.3
Name: yta-core
Version: 0.0.21
Summary: Youtube Autonomous Core
Author: danialcala94
Author-email: danielalcalavalera@gmail.com
Requires-Python: ==3.9
Classifier: Programming Language :: Python :: 3
Classifier: Programming Language :: Python :: 3.9
Requires-Dist: moviepy (>=2.0.0,<9.0.0)
Requires-Dist: yta_audio_narration (>=0.0.1,<1.0.0)
Requires-Dist: yta_audio_narration_google (>=0.0.1,<1.0.0)
Requires-Dist: yta_audio_narration_microsoft (>=0.0.1,<1.0.0)
Requires-Dist: yta_audio_silences (>=0.0.1,<1.0.0)
Requires-Dist: yta_audio_transcription (>=0.0.1,<1.0.0)
Requires-Dist: yta_constants (>=0.0.1,<1.0.0)
Requires-Dist: yta_file (>=0.0.1,<1.0.0)
Requires-Dist: yta_file_downloader (>=0.0.1,<1.0.0)
Requires-Dist: yta_general_utils (>=0.0.251,<1.0.0)
Requires-Dist: yta_image_advanced_ai (>=0.0.1,<1.0.0)
Requires-Dist: yta_mongo (>=0.0.1,<1.0.0)
Requires-Dist: yta_programming (>=0.0.1,<1.0.0)
Requires-Dist: yta_random (>=0.0.1,<1.0.0)
Requires-Dist: yta_shortcodes (>=0.0.1,<1.0.0)
Requires-Dist: yta_stock_downloader (>=0.0.1,<1.0.0)
Requires-Dist: yta_temp (>=0.0.1,<1.0.0)
Requires-Dist: yta_text (>=0.0.1,<1.0.0)
Requires-Dist: yta_validation (>=0.0.1,<1.0.0)
Requires-Dist: yta_video_advanced_effects (>=0.0.1,<1.0.0)
Requires-Dist: yta_video_advanced_premades (>=0.0.1,<1.0.0)
Requires-Dist: yta_video_base (>=0.0.1,<1.0.0)
Requires-Dist: yta_video_ffmpeg (>=0.0.1,<1.0.0)
Requires-Dist: yta_video_manim (>=0.0.1,<1.0.0)
Requires-Dist: yta_youtube (>=0.0.1,<1.0.0)
Requires-Dist: yta_youtube_enhanced (>=0.0.1,<1.0.0)
